<?xml version='1.0' encoding='UTF-8'?><factura version='1.1.0' id='comprobante'><infoTributaria><ambiente>2</ambiente><tipoEmision>1</tipoEmision><razonSocial>URQUIAGA MENDIETA CINTHYA EMPERATRIZ</razonSocial><nombreComercial>CACAO BEAUTY SHOP</nombreComercial><ruc>3050369739001</ruc><claveAcceso>1801202301305036973900120021000000000891234567810</claveAcceso><codDoc>01</codDoc><estab>002</estab><ptoEmi>100</ptoEmi><secuencial>000000089</secuencial><dirMatriz>PASEO DE LOS CAÑARIS  NUM 4-41 Y CACIQUE DUMA</dirMatriz></infoTributaria><infoFactura><fechaEmision>18/01/2023</fechaEmision><dirEstablecimiento>PASEO DE LOS CAÑARIS S/N Y CACIQUE DUMA</dirEstablecimiento><obligadoContabilidad>NO</obligadoContabilidad><tipoIdentificacionComprador>04</tipoIdentificacionComprador><razonSocialComprador>SERVIENTREGA ECUADOR S.A.</razonSocialComprador><identificacionComprador>0991285679001</identificacionComprador><totalSinImpuestos>677.49</totalSinImpuestos><totalDescuento>0</totalDescuento><totalConImpuestos><totalImpuesto><codigo>2</codigo><codigoPorcentaje>2</codigoPorcentaje><baseImponible>677.49</baseImponible><valor>81.3</valor></totalImpuesto></totalConImpuestos><propina>0.00</propina><importeTotal>758.79</importeTotal><moneda>DOLAR</moneda><pagos><pago><formaPago>20</formaPago><total>758.79</total></pago></pagos></infoFactura><detalles><detalle><codigoPrincipal>CARGA</codigoPrincipal><descripcion>COMISIONES SOBRE VENTAS CONTADO DEL MES DE DICIEMBRE</descripcion><cantidad>1</cantidad><precioUnitario>618.15</precioUnitario><descuento>0</descuento><precioTotalSinImpuesto>618.15</precioTotalSinImpuesto><impuestos><impuesto><codigo>2</codigo><codigoPorcentaje>2</codigoPorcentaje><tarifa>12</tarifa><baseImponible>618.15</baseImponible><valor>74.18</valor></impuesto></impuestos></detalle><detalle><codigoPrincipal>DOCUMENTO</codigoPrincipal><descripcion>COMISIONES SOBRE VENTAS CONTADO DEL MES DE DICIEMBRE</descripcion><cantidad>1</cantidad><precioUnitario>59.34</precioUnitario><descuento>0</descuento><precioTotalSinImpuesto>59.34</precioTotalSinImpuesto><impuestos><impuesto><codigo>2</codigo><codigoPorcentaje>2</codigoPorcentaje><tarifa>12</tarifa><baseImponible>59.34</baseImponible><valor>7.12</valor></impuesto></impuestos></detalle></detalles><infoAdicional><campoAdicional nombre='Direccion'>AV JUAN TANCA MARENGO Y CAMILO PONCE</campoAdicional><campoAdicional nombre='Telefono'>043732000</campoAdicional><campoAdicional nombre='Email'>rosa.quito@servientrega.com.ec</campoAdicional><campoAdicional nombre='Observaciones'> Contribuyente Régimen RIMPE   </campoAdicional></infoAdicional></factura>